Metadata-Version: 2.4
Name: test-mcp-server
Version: 0.1.3
Summary: Add your description here
Requires-Python: >=3.11
Requires-Dist: mcp>=1.7.1
